zjy_easyplot/__init__.py
zjy_easyplot/my_plot.py
zjy_easyplot-0.1.dist-info/LICENSE.txt
zjy_easyplot-0.1.dist-info/METADATA
zjy_easyplot-0.1.dist-info/WHEEL
zjy_easyplot-0.1.dist-info/top_level.txt
zjy_easyplot-0.1.dist-info/RECORD
