Metadata-Version: 2.1
Name: zjy-easyplot
Version: 0.1
Summary: 用于绘制函数图像
Home-page: https://github.com/Pythonlover2020/zjy_easyplot
Author: 朱江宇
Author-email: zhuhaibo8@163.com
License: MIT
Platform: UNKNOWN
Classifier: License :: OSI Approved :: MIT License
Classifier: Programming Language :: Python
Classifier: Programming Language :: Python :: 3
Classifier: Programming Language :: Python :: 3.6
Classifier: Programming Language :: Python :: Implementation :: CPython
Classifier: Programming Language :: Python :: Implementation :: PyPy
Requires-Python: >=3.5.0
Requires-Dist: numpy
Requires-Dist: matplotlib
